{
  "from": {
    "Name": "Mythic",
    "Description": "Mythic is a next-generation starter theme designed to help theme authors write elegant, intelligent, and modern code.",
    "Uri": "https://themehybrid.com/themes/mythic",
    "Author": "Justin Tadlock",
    "AuthorEmail": "justintadlock@gmail.com",
    "AuthorUri": "https://themehybrid.com"
  },
  "to": {
    "Name": "Mag",
    "Description": "Mythic is a next-generation starter theme designed to help theme authors write elegant, intelligent, and modern code.",
    "Uri": "https://themehybrid.com/themes/mythic",
    "Author": "Mithun Biswas",
    "AuthorEmail": "bhoot.biswas@gmail.com",
    "AuthorUri": "https://bengal-studio.com/"
  }
}